django_static_collector.py
django_static_collector-0.2.0.dist-info/METADATA
django_static_collector-0.2.0.dist-info/RECORD
django_static_collector-0.2.0.dist-info/WHEEL
django_static_collector-0.2.0.dist-info/entry_points.txt
django_static_collector-0.2.0.dist-info/top_level.txt
